{"uid":"EventStore.Rags.NameTranslators","isEii":false,"isExtensionMethod":false,"parent":{"uid":"EventStore.Rags","isEii":false,"isExtensionMethod":false,"name":[{"lang":"csharp","value":"EventStore.Rags"},{"lang":"vb","value":"EventStore.Rags"}],"nameWithType":[{"lang":"csharp","value":"EventStore.Rags"},{"lang":"vb","value":"EventStore.Rags"}],"fullName":[{"lang":"csharp","value":"EventStore.Rags"},{"lang":"vb","value":"EventStore.Rags"}],"specName":[{"lang":"csharp","value":"<xref uid=\"EventStore.Rags\" text=\"EventStore.Rags\" alt=\"EventStore.Rags\"/>"},{"lang":"vb","value":"<xref uid=\"EventStore.Rags\" text=\"EventStore.Rags\" alt=\"EventStore.Rags\"/>"}],"level":0.0},"children":[{"inMethod":true,"typePropertyName":"inMethod","id":"methods","children":[{"uid":"EventStore.Rags.NameTranslators.CombineByPascalCase(System.String,System.String)","isEii":false,"isExtensionMethod":false,"parent":"EventStore.Rags.NameTranslators","isExternal":false,"name":[{"lang":"csharp","value":"CombineByPascalCase(String, String)"},{"lang":"vb","value":"CombineByPascalCase(String, String)"}],"nameWithType":[{"lang":"csharp","value":"NameTranslators.CombineByPascalCase(String, String)"},{"lang":"vb","value":"NameTranslators.CombineByPascalCase(String, String)"}],"fullName":[{"lang":"csharp","value":"EventStore.Rags.NameTranslators.CombineByPascalCase(System.String, System.String)"},{"lang":"vb","value":"EventStore.Rags.NameTranslators.CombineByPascalCase(System.String, System.String)"}],"specName":[{"lang":"csharp","value":"<xref uid=\"EventStore.Rags.NameTranslators.CombineByPascalCase(System.String,System.String)\" text=\"CombineByPascalCase(String, String)\" alt=\"EventStore.Rags.NameTranslators.CombineByPascalCase(System.String, System.String)\"/>"},{"lang":"vb","value":"<xref uid=\"EventStore.Rags.NameTranslators.CombineByPascalCase(System.String,System.String)\" text=\"CombineByPascalCase(String, String)\" alt=\"EventStore.Rags.NameTranslators.CombineByPascalCase(System.String, System.String)\"/>"}],"syntax":{"content":[{"lang":"csharp","value":"public static string CombineByPascalCase(string name, string token)"},{"lang":"vb","value":"Public Shared Function CombineByPascalCase(name As String, token As String) As String"}],"parameters":[{"id":"name","type":{"uid":"System.String","name":[{"lang":"csharp","value":"String"},{"lang":"vb","value":"String"}],"nameWithType":[{"lang":"csharp","value":"String"},{"lang":"vb","value":"String"}],"fullName":[{"lang":"csharp","value":"System.String"},{"lang":"vb","value":"System.String"}],"specName":[{"lang":"csharp","value":"<xref uid=\"System.String\" text=\"String\" alt=\"System.String\"/>"},{"lang":"vb","value":"<xref uid=\"System.String\" text=\"String\" alt=\"System.String\"/>"}]}},{"id":"token","type":{"uid":"System.String","name":[{"lang":"csharp","value":"String"},{"lang":"vb","value":"String"}],"nameWithType":[{"lang":"csharp","value":"String"},{"lang":"vb","value":"String"}],"fullName":[{"lang":"csharp","value":"System.String"},{"lang":"vb","value":"System.String"}],"specName":[{"lang":"csharp","value":"<xref uid=\"System.String\" text=\"String\" alt=\"System.String\"/>"},{"lang":"vb","value":"<xref uid=\"System.String\" text=\"String\" alt=\"System.String\"/>"}]}}],"return":{"type":{"uid":"System.String","name":[{"lang":"csharp","value":"String"},{"lang":"vb","value":"String"}],"nameWithType":[{"lang":"csharp","value":"String"},{"lang":"vb","value":"String"}],"fullName":[{"lang":"csharp","value":"System.String"},{"lang":"vb","value":"System.String"}],"specName":[{"lang":"csharp","value":"<xref uid=\"System.String\" text=\"String\" alt=\"System.String\"/>"},{"lang":"vb","value":"<xref uid=\"System.String\" text=\"String\" alt=\"System.String\"/>"}]}}},"source":{"id":"CombineByPascalCase","path":"/Users/chrisward/Workspace/EventStore/EventStore/src/EventStore.Rags/NameTranslators.cs","startLine":6.0,"endLine":0.0,"isExternal":false},"assemblies":["EventStore.Rags"],"namespace":"EventStore.Rags","overload":{"uid":"EventStore.Rags.NameTranslators.CombineByPascalCase*","name":[{"lang":"csharp","value":"CombineByPascalCase"},{"lang":"vb","value":"CombineByPascalCase"}],"nameWithType":[{"lang":"csharp","value":"NameTranslators.CombineByPascalCase"},{"lang":"vb","value":"NameTranslators.CombineByPascalCase"}],"fullName":[{"lang":"csharp","value":"EventStore.Rags.NameTranslators.CombineByPascalCase"},{"lang":"vb","value":"EventStore.Rags.NameTranslators.CombineByPascalCase"}],"specName":[{"lang":"csharp","value":"<xref uid=\"EventStore.Rags.NameTranslators.CombineByPascalCase*\" text=\"CombineByPascalCase\" alt=\"EventStore.Rags.NameTranslators.CombineByPascalCase\"/>"},{"lang":"vb","value":"<xref uid=\"EventStore.Rags.NameTranslators.CombineByPascalCase*\" text=\"CombineByPascalCase\" alt=\"EventStore.Rags.NameTranslators.CombineByPascalCase\"/>"}],"id":"EventStore_Rags_NameTranslators_CombineByPascalCase_"},"level":0.0,"modifiers.csharp":["public","static"],"modifiers.vb":["Public","Shared"],"type":"method","summary":null,"platform":null,"docurl":"","sourceurl":"","remarks":null,"conceptual":null,"implements":null,"example":null,"seealso":null,"id":"EventStore_Rags_NameTranslators_CombineByPascalCase_System_String_System_String_","hideTitleType":false,"hideSubtitle":false},{"uid":"EventStore.Rags.NameTranslators.None(System.String)","isEii":false,"isExtensionMethod":false,"parent":"EventStore.Rags.NameTranslators","isExternal":false,"name":[{"lang":"csharp","value":"None(String)"},{"lang":"vb","value":"None(String)"}],"nameWithType":[{"lang":"csharp","value":"NameTranslators.None(String)"},{"lang":"vb","value":"NameTranslators.None(String)"}],"fullName":[{"lang":"csharp","value":"EventStore.Rags.NameTranslators.None(System.String)"},{"lang":"vb","value":"EventStore.Rags.NameTranslators.None(System.String)"}],"specName":[{"lang":"csharp","value":"<xref uid=\"EventStore.Rags.NameTranslators.None(System.String)\" text=\"None(String)\" alt=\"EventStore.Rags.NameTranslators.None(System.String)\"/>"},{"lang":"vb","value":"<xref uid=\"EventStore.Rags.NameTranslators.None(System.String)\" text=\"None(String)\" alt=\"EventStore.Rags.NameTranslators.None(System.String)\"/>"}],"syntax":{"content":[{"lang":"csharp","value":"public static string None(string name)"},{"lang":"vb","value":"Public Shared Function None(name As String) As String"}],"parameters":[{"id":"name","type":{"uid":"System.String","name":[{"lang":"csharp","value":"String"},{"lang":"vb","value":"String"}],"nameWithType":[{"lang":"csharp","value":"String"},{"lang":"vb","value":"String"}],"fullName":[{"lang":"csharp","value":"System.String"},{"lang":"vb","value":"System.String"}],"specName":[{"lang":"csharp","value":"<xref uid=\"System.String\" text=\"String\" alt=\"System.String\"/>"},{"lang":"vb","value":"<xref uid=\"System.String\" text=\"String\" alt=\"System.String\"/>"}]}}],"return":{"type":{"uid":"System.String","name":[{"lang":"csharp","value":"String"},{"lang":"vb","value":"String"}],"nameWithType":[{"lang":"csharp","value":"String"},{"lang":"vb","value":"String"}],"fullName":[{"lang":"csharp","value":"System.String"},{"lang":"vb","value":"System.String"}],"specName":[{"lang":"csharp","value":"<xref uid=\"System.String\" text=\"String\" alt=\"System.String\"/>"},{"lang":"vb","value":"<xref uid=\"System.String\" text=\"String\" alt=\"System.String\"/>"}]}}},"source":{"id":"None","path":"/Users/chrisward/Workspace/EventStore/EventStore/src/EventStore.Rags/NameTranslators.cs","startLine":12.0,"endLine":0.0,"isExternal":false},"assemblies":["EventStore.Rags"],"namespace":"EventStore.Rags","overload":{"uid":"EventStore.Rags.NameTranslators.None*","name":[{"lang":"csharp","value":"None"},{"lang":"vb","value":"None"}],"nameWithType":[{"lang":"csharp","value":"NameTranslators.None"},{"lang":"vb","value":"NameTranslators.None"}],"fullName":[{"lang":"csharp","value":"EventStore.Rags.NameTranslators.None"},{"lang":"vb","value":"EventStore.Rags.NameTranslators.None"}],"specName":[{"lang":"csharp","value":"<xref uid=\"EventStore.Rags.NameTranslators.None*\" text=\"None\" alt=\"EventStore.Rags.NameTranslators.None\"/>"},{"lang":"vb","value":"<xref uid=\"EventStore.Rags.NameTranslators.None*\" text=\"None\" alt=\"EventStore.Rags.NameTranslators.None\"/>"}],"id":"EventStore_Rags_NameTranslators_None_"},"level":0.0,"modifiers.csharp":["public","static"],"modifiers.vb":["Public","Shared"],"type":"method","summary":null,"platform":null,"docurl":"","sourceurl":"","remarks":null,"conceptual":null,"implements":null,"example":null,"seealso":null,"id":"EventStore_Rags_NameTranslators_None_System_String_","hideTitleType":false,"hideSubtitle":false},{"uid":"EventStore.Rags.NameTranslators.PrefixEnvironmentVariable(System.String,System.String)","isEii":false,"isExtensionMethod":false,"parent":"EventStore.Rags.NameTranslators","isExternal":false,"name":[{"lang":"csharp","value":"PrefixEnvironmentVariable(String, String)"},{"lang":"vb","value":"PrefixEnvironmentVariable(String, String)"}],"nameWithType":[{"lang":"csharp","value":"NameTranslators.PrefixEnvironmentVariable(String, String)"},{"lang":"vb","value":"NameTranslators.PrefixEnvironmentVariable(String, String)"}],"fullName":[{"lang":"csharp","value":"EventStore.Rags.NameTranslators.PrefixEnvironmentVariable(System.String, System.String)"},{"lang":"vb","value":"EventStore.Rags.NameTranslators.PrefixEnvironmentVariable(System.String, System.String)"}],"specName":[{"lang":"csharp","value":"<xref uid=\"EventStore.Rags.NameTranslators.PrefixEnvironmentVariable(System.String,System.String)\" text=\"PrefixEnvironmentVariable(String, String)\" alt=\"EventStore.Rags.NameTranslators.PrefixEnvironmentVariable(System.String, System.String)\"/>"},{"lang":"vb","value":"<xref uid=\"EventStore.Rags.NameTranslators.PrefixEnvironmentVariable(System.String,System.String)\" text=\"PrefixEnvironmentVariable(String, String)\" alt=\"EventStore.Rags.NameTranslators.PrefixEnvironmentVariable(System.String, System.String)\"/>"}],"syntax":{"content":[{"lang":"csharp","value":"public static string PrefixEnvironmentVariable(string name, string prefix)"},{"lang":"vb","value":"Public Shared Function PrefixEnvironmentVariable(name As String, prefix As String) As String"}],"parameters":[{"id":"name","type":{"uid":"System.String","name":[{"lang":"csharp","value":"String"},{"lang":"vb","value":"String"}],"nameWithType":[{"lang":"csharp","value":"String"},{"lang":"vb","value":"String"}],"fullName":[{"lang":"csharp","value":"System.String"},{"lang":"vb","value":"System.String"}],"specName":[{"lang":"csharp","value":"<xref uid=\"System.String\" text=\"String\" alt=\"System.String\"/>"},{"lang":"vb","value":"<xref uid=\"System.String\" text=\"String\" alt=\"System.String\"/>"}]}},{"id":"prefix","type":{"uid":"System.String","name":[{"lang":"csharp","value":"String"},{"lang":"vb","value":"String"}],"nameWithType":[{"lang":"csharp","value":"String"},{"lang":"vb","value":"String"}],"fullName":[{"lang":"csharp","value":"System.String"},{"lang":"vb","value":"System.String"}],"specName":[{"lang":"csharp","value":"<xref uid=\"System.String\" text=\"String\" alt=\"System.String\"/>"},{"lang":"vb","value":"<xref uid=\"System.String\" text=\"String\" alt=\"System.String\"/>"}]}}],"return":{"type":{"uid":"System.String","name":[{"lang":"csharp","value":"String"},{"lang":"vb","value":"String"}],"nameWithType":[{"lang":"csharp","value":"String"},{"lang":"vb","value":"String"}],"fullName":[{"lang":"csharp","value":"System.String"},{"lang":"vb","value":"System.String"}],"specName":[{"lang":"csharp","value":"<xref uid=\"System.String\" text=\"String\" alt=\"System.String\"/>"},{"lang":"vb","value":"<xref uid=\"System.String\" text=\"String\" alt=\"System.String\"/>"}]}}},"source":{"id":"PrefixEnvironmentVariable","path":"/Users/chrisward/Workspace/EventStore/EventStore/src/EventStore.Rags/NameTranslators.cs","startLine":2.0,"endLine":0.0,"isExternal":false},"assemblies":["EventStore.Rags"],"namespace":"EventStore.Rags","overload":{"uid":"EventStore.Rags.NameTranslators.PrefixEnvironmentVariable*","name":[{"lang":"csharp","value":"PrefixEnvironmentVariable"},{"lang":"vb","value":"PrefixEnvironmentVariable"}],"nameWithType":[{"lang":"csharp","value":"NameTranslators.PrefixEnvironmentVariable"},{"lang":"vb","value":"NameTranslators.PrefixEnvironmentVariable"}],"fullName":[{"lang":"csharp","value":"EventStore.Rags.NameTranslators.PrefixEnvironmentVariable"},{"lang":"vb","value":"EventStore.Rags.NameTranslators.PrefixEnvironmentVariable"}],"specName":[{"lang":"csharp","value":"<xref uid=\"EventStore.Rags.NameTranslators.PrefixEnvironmentVariable*\" text=\"PrefixEnvironmentVariable\" alt=\"EventStore.Rags.NameTranslators.PrefixEnvironmentVariable\"/>"},{"lang":"vb","value":"<xref uid=\"EventStore.Rags.NameTranslators.PrefixEnvironmentVariable*\" text=\"PrefixEnvironmentVariable\" alt=\"EventStore.Rags.NameTranslators.PrefixEnvironmentVariable\"/>"}],"id":"EventStore_Rags_NameTranslators_PrefixEnvironmentVariable_"},"level":0.0,"modifiers.csharp":["public","static"],"modifiers.vb":["Public","Shared"],"type":"method","summary":null,"platform":null,"docurl":"","sourceurl":"","remarks":null,"conceptual":null,"implements":null,"example":null,"seealso":null,"id":"EventStore_Rags_NameTranslators_PrefixEnvironmentVariable_System_String_System_String_","hideTitleType":false,"hideSubtitle":false}]}],"langs":["csharp","vb"],"name":[{"lang":"csharp","value":"NameTranslators"},{"lang":"vb","value":"NameTranslators"}],"nameWithType":[{"lang":"csharp","value":"NameTranslators"},{"lang":"vb","value":"NameTranslators"}],"fullName":[{"lang":"csharp","value":"EventStore.Rags.NameTranslators"},{"lang":"vb","value":"EventStore.Rags.NameTranslators"}],"type":"class","source":{"id":"NameTranslators","path":"/Users/chrisward/Workspace/EventStore/EventStore/src/EventStore.Rags/NameTranslators.cs","startLine":1.0,"endLine":0.0,"isExternal":false},"assemblies":["EventStore.Rags"],"namespace":{"uid":"EventStore.Rags","isEii":false,"isExtensionMethod":false,"name":[{"lang":"csharp","value":"EventStore.Rags"},{"lang":"vb","value":"EventStore.Rags"}],"nameWithType":[{"lang":"csharp","value":"EventStore.Rags"},{"lang":"vb","value":"EventStore.Rags"}],"fullName":[{"lang":"csharp","value":"EventStore.Rags"},{"lang":"vb","value":"EventStore.Rags"}],"specName":[{"lang":"csharp","value":"<xref uid=\"EventStore.Rags\" text=\"EventStore.Rags\" alt=\"EventStore.Rags\"/>"},{"lang":"vb","value":"<xref uid=\"EventStore.Rags\" text=\"EventStore.Rags\" alt=\"EventStore.Rags\"/>"}],"level":0.0},"syntax":{"content":[{"lang":"csharp","value":"public static class NameTranslators"},{"lang":"vb","value":"Public Module NameTranslators"}]},"inheritance":[{"uid":"System.Object","isEii":false,"isExtensionMethod":false,"parent":"System","isExternal":true,"name":[{"lang":"csharp","value":"Object"},{"lang":"vb","value":"Object"}],"nameWithType":[{"lang":"csharp","value":"Object"},{"lang":"vb","value":"Object"}],"fullName":[{"lang":"csharp","value":"System.Object"},{"lang":"vb","value":"System.Object"}],"specName":[{"lang":"csharp","value":"<xref uid=\"System.Object\" text=\"Object\" alt=\"System.Object\"/>"},{"lang":"vb","value":"<xref uid=\"System.Object\" text=\"Object\" alt=\"System.Object\"/>"}],"level":0.0,"index":0.0}],"level":1.0,"inheritedMembers":[{"uid":"System.Object.Equals(System.Object)","isEii":false,"isExtensionMethod":false,"parent":"System.Object","isExternal":true,"name":[{"lang":"csharp","value":"Equals(Object)"},{"lang":"vb","value":"Equals(Object)"}],"nameWithType":[{"lang":"csharp","value":"Object.Equals(Object)"},{"lang":"vb","value":"Object.Equals(Object)"}],"fullName":[{"lang":"csharp","value":"System.Object.Equals(System.Object)"},{"lang":"vb","value":"System.Object.Equals(System.Object)"}],"specName":[{"lang":"csharp","value":"<xref uid=\"System.Object.Equals(System.Object)\" text=\"Equals\" alt=\"System.Object.Equals\"/>(<xref uid=\"System.Object\" text=\"Object\" alt=\"System.Object\"/>)"},{"lang":"vb","value":"<xref uid=\"System.Object.Equals(System.Object)\" text=\"Equals\" alt=\"System.Object.Equals\"/>(<xref uid=\"System.Object\" text=\"Object\" alt=\"System.Object\"/>)"}],"level":0.0},{"uid":"System.Object.Equals(System.Object,System.Object)","isEii":false,"isExtensionMethod":false,"parent":"System.Object","isExternal":true,"name":[{"lang":"csharp","value":"Equals(Object, Object)"},{"lang":"vb","value":"Equals(Object, Object)"}],"nameWithType":[{"lang":"csharp","value":"Object.Equals(Object, Object)"},{"lang":"vb","value":"Object.Equals(Object, Object)"}],"fullName":[{"lang":"csharp","value":"System.Object.Equals(System.Object, System.Object)"},{"lang":"vb","value":"System.Object.Equals(System.Object, System.Object)"}],"specName":[{"lang":"csharp","value":"<xref uid=\"System.Object.Equals(System.Object,System.Object)\" text=\"Equals\" alt=\"System.Object.Equals\"/>(<xref uid=\"System.Object\" text=\"Object\" alt=\"System.Object\"/>, <xref uid=\"System.Object\" text=\"Object\" alt=\"System.Object\"/>)"},{"lang":"vb","value":"<xref uid=\"System.Object.Equals(System.Object,System.Object)\" text=\"Equals\" alt=\"System.Object.Equals\"/>(<xref uid=\"System.Object\" text=\"Object\" alt=\"System.Object\"/>, <xref uid=\"System.Object\" text=\"Object\" alt=\"System.Object\"/>)"}],"level":0.0},{"uid":"System.Object.GetHashCode","isEii":false,"isExtensionMethod":false,"parent":"System.Object","isExternal":true,"name":[{"lang":"csharp","value":"GetHashCode()"},{"lang":"vb","value":"GetHashCode()"}],"nameWithType":[{"lang":"csharp","value":"Object.GetHashCode()"},{"lang":"vb","value":"Object.GetHashCode()"}],"fullName":[{"lang":"csharp","value":"System.Object.GetHashCode()"},{"lang":"vb","value":"System.Object.GetHashCode()"}],"specName":[{"lang":"csharp","value":"<xref uid=\"System.Object.GetHashCode\" text=\"GetHashCode\" alt=\"System.Object.GetHashCode\"/>()"},{"lang":"vb","value":"<xref uid=\"System.Object.GetHashCode\" text=\"GetHashCode\" alt=\"System.Object.GetHashCode\"/>()"}],"level":0.0},{"uid":"System.Object.GetType","isEii":false,"isExtensionMethod":false,"parent":"System.Object","isExternal":true,"name":[{"lang":"csharp","value":"GetType()"},{"lang":"vb","value":"GetType()"}],"nameWithType":[{"lang":"csharp","value":"Object.GetType()"},{"lang":"vb","value":"Object.GetType()"}],"fullName":[{"lang":"csharp","value":"System.Object.GetType()"},{"lang":"vb","value":"System.Object.GetType()"}],"specName":[{"lang":"csharp","value":"<xref uid=\"System.Object.GetType\" text=\"GetType\" alt=\"System.Object.GetType\"/>()"},{"lang":"vb","value":"<xref uid=\"System.Object.GetType\" text=\"GetType\" alt=\"System.Object.GetType\"/>()"}],"level":0.0},{"uid":"System.Object.MemberwiseClone","isEii":false,"isExtensionMethod":false,"parent":"System.Object","isExternal":true,"name":[{"lang":"csharp","value":"MemberwiseClone()"},{"lang":"vb","value":"MemberwiseClone()"}],"nameWithType":[{"lang":"csharp","value":"Object.MemberwiseClone()"},{"lang":"vb","value":"Object.MemberwiseClone()"}],"fullName":[{"lang":"csharp","value":"System.Object.MemberwiseClone()"},{"lang":"vb","value":"System.Object.MemberwiseClone()"}],"specName":[{"lang":"csharp","value":"<xref uid=\"System.Object.MemberwiseClone\" text=\"MemberwiseClone\" alt=\"System.Object.MemberwiseClone\"/>()"},{"lang":"vb","value":"<xref uid=\"System.Object.MemberwiseClone\" text=\"MemberwiseClone\" alt=\"System.Object.MemberwiseClone\"/>()"}],"level":0.0},{"uid":"System.Object.ReferenceEquals(System.Object,System.Object)","isEii":false,"isExtensionMethod":false,"parent":"System.Object","isExternal":true,"name":[{"lang":"csharp","value":"ReferenceEquals(Object, Object)"},{"lang":"vb","value":"ReferenceEquals(Object, Object)"}],"nameWithType":[{"lang":"csharp","value":"Object.ReferenceEquals(Object, Object)"},{"lang":"vb","value":"Object.ReferenceEquals(Object, Object)"}],"fullName":[{"lang":"csharp","value":"System.Object.ReferenceEquals(System.Object, System.Object)"},{"lang":"vb","value":"System.Object.ReferenceEquals(System.Object, System.Object)"}],"specName":[{"lang":"csharp","value":"<xref uid=\"System.Object.ReferenceEquals(System.Object,System.Object)\" text=\"ReferenceEquals\" alt=\"System.Object.ReferenceEquals\"/>(<xref uid=\"System.Object\" text=\"Object\" alt=\"System.Object\"/>, <xref uid=\"System.Object\" text=\"Object\" alt=\"System.Object\"/>)"},{"lang":"vb","value":"<xref uid=\"System.Object.ReferenceEquals(System.Object,System.Object)\" text=\"ReferenceEquals\" alt=\"System.Object.ReferenceEquals\"/>(<xref uid=\"System.Object\" text=\"Object\" alt=\"System.Object\"/>, <xref uid=\"System.Object\" text=\"Object\" alt=\"System.Object\"/>)"}],"level":0.0},{"uid":"System.Object.ToString","isEii":false,"isExtensionMethod":false,"parent":"System.Object","isExternal":true,"name":[{"lang":"csharp","value":"ToString()"},{"lang":"vb","value":"ToString()"}],"nameWithType":[{"lang":"csharp","value":"Object.ToString()"},{"lang":"vb","value":"Object.ToString()"}],"fullName":[{"lang":"csharp","value":"System.Object.ToString()"},{"lang":"vb","value":"System.Object.ToString()"}],"specName":[{"lang":"csharp","value":"<xref uid=\"System.Object.ToString\" text=\"ToString\" alt=\"System.Object.ToString\"/>()"},{"lang":"vb","value":"<xref uid=\"System.Object.ToString\" text=\"ToString\" alt=\"System.Object.ToString\"/>()"}],"level":0.0}],"_docfxVersion":"2.43.3.0","_disableBreadcrumb":true,"_enableSearch":true,"_gitContribute":{"branch":"master"},"_appFaviconPath":"assets/favicon.ico","_appTitle":"Event Store","_appFooter":"&copy; 2019 Event Store Limited","_disableNavbar":false,"_disableToc":true,"_systemKeys":["uid","isEii","isExtensionMethod","parent","children","href","langs","name","nameWithType","fullName","type","source","documentation","assemblies","namespace","summary","remarks","example","syntax","overridden","overload","exceptions","seealso","see","inheritance","derivedClasses","level","implements","inheritedMembers","extensionMethods","conceptual","platform","attributes","additionalNotes"],"_lang":"csharp","_tocPath":"toc.html","_navPath":"toc.html","_rel":"../../","_path":"dotnet-api/code/EventStore.Rags.NameTranslators.html","_key":"dotnet-api/code/EventStore.Rags.NameTranslators.yml","_navRel":"../../toc.html","_tocRel":"../../toc.html","_navKey":"~/toc.yml","_tocKey":"~/toc.yml","__global":{"classesInSubtitle":"Classes","structsInSubtitle":"Structs","interfacesInSubtitle":"Interfaces","enumsInSubtitle":"Enums","delegatesInSubtitle":"Delegates","constructorsInSubtitle":"Constructors","fieldsInSubtitle":"Fields","propertiesInSubtitle":"Properties","methodsInSubtitle":"Methods","eventsInSubtitle":"Events","operatorsInSubtitle":"Operators","eiisInSubtitle":"Explicit Interface Implementations","functionsInSubtitle":"Functions","membersInSubtitle":"Members","improveThisDoc":"Improve this Doc","viewSource":"View Source","inheritance":"Inheritance","inheritedMembers":"Inherited Members","namespace":"Namespace","assembly":"Assembly","syntax":"Syntax","overrides":"Overrides","implements":"Implements","remarks":"Remarks","examples":"Examples","seealso":"See Also","declaration":"Declaration","parameters":"Parameters","typeParameters":"Type Parameters","type":"Type","name":"Name","description":"Description","returns":"Returns","fieldValue":"Field Value","propertyValue":"Property Value","eventType":"Event Type","exceptions":"Exceptions","condition":"Condition","extensionMethods":"Extension Methods","note":"<h5>Note</h5>","warning":"<h5>Warning</h5>","tip":"<h5>Tip</h5>","important":"<h5>Important</h5>","caution":"<h5>Caution</h5>","next":"<h5>Next Steps</h5>","_shared":{}},"docurl":"","sourceurl":"","summary":null,"remarks":null,"conceptual":null,"implements":null,"example":null,"seealso":null,"id":"EventStore_Rags_NameTranslators","hideTitleType":false,"hideSubtitle":false,"isClass":true,"inClass":true}